logs_proto/__init__.py
logs_proto/logs_pb2.py
logs_proto/logs_pb2_grpc.py
loggylog_grpc-0.1.3.dist-info/METADATA
loggylog_grpc-0.1.3.dist-info/WHEEL
loggylog_grpc-0.1.3.dist-info/top_level.txt
loggylog_grpc-0.1.3.dist-info/RECORD
