Metadata-Version: 2.1
Name: loggylog-grpc
Version: 0.1.3
Summary: Generated code for loggylog related python code
Home-page: UNKNOWN
Author: Vagif Mammadaliyev
License: UNKNOWN
Platform: UNKNOWN
Requires-Python: >=3.7
Requires-Dist: grpcio (~=1.36.1)
Requires-Dist: grpcio-tools (~=1.36.1)
